Ensembl_converter/__init__.py
Ensembl_converter/converter.py
tests/__init__.py
tests/test_converter.py
ensembl_converter-0.0.1.dist-info/LICENSE
ensembl_converter-0.0.1.dist-info/METADATA
ensembl_converter-0.0.1.dist-info/WHEEL
ensembl_converter-0.0.1.dist-info/top_level.txt
ensembl_converter-0.0.1.dist-info/RECORD
