Metadata-Version: 2.1
Name: ensembl-converter
Version: 0.0.1
Summary: Convert Ensembl IDs to gene symbols
Home-page: https://github.com/AmmarMalik93/ensembl-converter
Author: Muhammad Ammar Malik
Author-email: malik.ammar1993@gmail.com
License: UNKNOWN
Platform: UNKNOWN
Classifier: Programming Language :: Python :: 3
Classifier: License :: OSI Approved :: MIT License
Classifier: Operating System :: OS Independent
Requires-Python: >=3.6
Requires-Dist: numpy
Requires-Dist: pandas
Requires-Dist: tqdm
Requires-Dist: requests
